resume_generator_mcp/__init__.py
resume_generator_mcp/__main__.py
resume_generator_mcp/server.py
resume_generator_mcp-1.7.1.dist-info/METADATA
resume_generator_mcp-1.7.1.dist-info/WHEEL
resume_generator_mcp-1.7.1.dist-info/entry_points.txt
resume_generator_mcp-1.7.1.dist-info/licenses/LICENSE
resume_generator_mcp-1.7.1.dist-info/RECORD
