Metadata-Version: 2.4
Name: resume-generator-mcp
Version: 1.7.1
Summary: MCP server for generating professional PDF resumes from YAML/JSON data
Project-URL: Homepage, https://github.com/ssarraju/wrok-docx
Project-URL: Documentation, https://github.com/ssarraju/wrok-docx#readme
Project-URL: Repository, https://github.com/ssarraju/wrok-docx
Project-URL: Issues, https://github.com/ssarraju/wrok-docx/issues
Author-email: Sravan Sarraju <sravan.sarraju@gmail.com>
License: MIT
License-File: LICENSE
Keywords: ai,claude,generator,mcp,pdf,resume
Classifier: Development Status :: 4 - Beta
Classifier: Intended Audience :: Developers
Classifier: License :: OSI Approved :: MIT License
Classifier: Programming Language :: Python :: 3
Classifier: Programming Language :: Python :: 3.10
Classifier: Programming Language :: Python :: 3.11
Classifier: Programming Language :: Python :: 3.12
Classifier: Topic :: Software Development :: Libraries :: Python Modules
Requires-Python: >=3.10
Requires-Dist: mcp>=1.2.0
Requires-Dist: pyyaml>=6.0.1
Requires-Dist: requests>=2.31.0
